{"status":"ok","data":[{"id":67967,"name":"GINTU","provinceId":67393,"provinceName":"SULAWESI TENGAH","regencyId":67866,"regencyName":"POSO","districtId":67966,"districtName":"LORE SELATAN"},{"id":67968,"name":"RUNDE","provinceId":67393,"provinceName":"SULAWESI TENGAH","regencyId":67866,"regencyName":"POSO","districtId":67966,"districtName":"LORE SELATAN"},{"id":67969,"name":"BADANGKAIA","provinceId":67393,"provinceName":"SULAWESI TENGAH","regencyId":67866,"regencyName":"POSO","districtId":67966,"districtName":"LORE SELATAN"},{"id":67970,"name":"BAKEKAU","provinceId":67393,"provinceName":"SULAWESI TENGAH","regencyId":67866,"regencyName":"POSO","districtId":67966,"districtName":"LORE SELATAN"},{"id":67971,"name":"BULILI","provinceId":67393,"provinceName":"SULAWESI TENGAH","regencyId":67866,"regencyName":"POSO","districtId":67966,"districtName":"LORE SELATAN"},{"id":67972,"name":"BEWA","provinceId":67393,"provinceName":"SULAWESI TENGAH","regencyId":67866,"regencyName":"POSO","districtId":67966,"districtName":"LORE SELATAN"},{"id":67973,"name":"PADA","provinceId":67393,"provinceName":"SULAWESI TENGAH","regencyId":67866,"regencyName":"POSO","districtId":67966,"districtName":"LORE SELATAN"},{"id":67974,"name":"BOMBA","provinceId":67393,"provinceName":"SULAWESI TENGAH","regencyId":67866,"regencyName":"POSO","districtId":67966,"districtName":"LORE SELATAN"}]}