{"status":"ok","data":{"regionNames":["IDN","GORONTALO","GORONTALO UTARA","SUMALATA TIMUR"],"regionIds":[0,74716,75301,83775],"ts":1556247235,"tpsDiffCount":0,"tpsCount":19,"votes":{"01":{"kpu":1654,"kawalPemilu":1654},"02":{"kpu":1895,"kawalPemilu":1895}},"childs":{"75346":{"id":75346,"name":"BULADU","ts":1556247221,"tpsCount":3,"tpsDiffCount":0,"votes":{"01":{"kpu":168,"kawalPemilu":168},"02":{"kpu":321,"kawalPemilu":321}}},"75347":{"id":75347,"name":"WUBUDU","ts":1556247222,"tpsCount":3,"tpsDiffCount":0,"votes":{"01":{"kpu":284,"kawalPemilu":284},"02":{"kpu":225,"kawalPemilu":225}}},"75349":{"id":75349,"name":"DULUKAPA","ts":1556247224,"tpsCount":3,"tpsDiffCount":0,"votes":{"01":{"kpu":217,"kawalPemilu":217},"02":{"kpu":419,"kawalPemilu":419}}},"85947":{"id":85947,"name":"DEME DUA","ts":1556247228,"tpsCount":3,"tpsDiffCount":0,"votes":{"01":{"kpu":230,"kawalPemilu":230},"02":{"kpu":313,"kawalPemilu":313}}},"85948":{"id":85948,"name":"BUBALANGO","ts":1556247230,"tpsCount":1,"tpsDiffCount":0,"votes":{"01":{"kpu":130,"kawalPemilu":130},"02":{"kpu":45,"kawalPemilu":45}}},"85949":{"id":85949,"name":"MOTIHELUMO","ts":1556247231,"tpsCount":3,"tpsDiffCount":0,"votes":{"01":{"kpu":257,"kawalPemilu":257},"02":{"kpu":375,"kawalPemilu":375}}},"85950":{"id":85950,"name":"KOLUWOKA","ts":1556247233,"tpsCount":1,"tpsDiffCount":0,"votes":{"01":{"kpu":136,"kawalPemilu":136},"02":{"kpu":81,"kawalPemilu":81}}},"90214":{"id":90214,"name":"HULAWA","ts":1556247235,"tpsCount":2,"tpsDiffCount":0,"votes":{"01":{"kpu":232,"kawalPemilu":232},"02":{"kpu":116,"kawalPemilu":116}}}}}}