{"status":"ok","data":{"regionNames":["IDN","SUMATERA SELATAN","MUSI BANYUASIN","LAIS"],"regionIds":[0,17404,18942,18958],"ts":1556185473,"tpsDiffCount":0,"tpsCount":19,"votes":{"01":{"kpu":619,"kawalPemilu":619},"02":{"kpu":3169,"kawalPemilu":3169}},"childs":{"18963":{"id":18963,"name":"LAIS","ts":1556185466,"tpsCount":1,"tpsDiffCount":0,"votes":{"01":{"kpu":65,"kawalPemilu":65},"02":{"kpu":166,"kawalPemilu":166}}},"18964":{"id":18964,"name":"TELUK","ts":1556185467,"tpsCount":8,"tpsDiffCount":0,"votes":{"01":{"kpu":177,"kawalPemilu":177},"02":{"kpu":1400,"kawalPemilu":1400}}},"18965":{"id":18965,"name":"EPIL","ts":1556185469,"tpsCount":5,"tpsDiffCount":0,"votes":{"01":{"kpu":95,"kawalPemilu":95},"02":{"kpu":915,"kawalPemilu":915}}},"18967":{"id":18967,"name":"TELUK KIJING I","ts":1556185470,"tpsCount":1,"tpsDiffCount":0,"votes":{"01":{"kpu":20,"kawalPemilu":20},"02":{"kpu":136,"kawalPemilu":136}}},"18969":{"id":18969,"name":"TELUK KIJING III","ts":1556185473,"tpsCount":4,"tpsDiffCount":0,"votes":{"01":{"kpu":262,"kawalPemilu":262},"02":{"kpu":552,"kawalPemilu":552}}}}}}