{"status":"ok","data":[{"id":35155,"name":"KUPANGAN","provinceId":32676,"provinceName":"JAWA TENGAH","regencyId":34900,"regencyName":"WONOSOBO","districtId":35154,"districtName":"SUKOHARJO"},{"id":35156,"name":"MERGOSARI","provinceId":32676,"provinceName":"JAWA TENGAH","regencyId":34900,"regencyName":"WONOSOBO","districtId":35154,"districtName":"SUKOHARJO"},{"id":35157,"name":"SUKOHARJO","provinceId":32676,"provinceName":"JAWA TENGAH","regencyId":34900,"regencyName":"WONOSOBO","districtId":35154,"districtName":"SUKOHARJO"},{"id":35158,"name":"ROGOJATI","provinceId":32676,"provinceName":"JAWA TENGAH","regencyId":34900,"regencyName":"WONOSOBO","districtId":35154,"districtName":"SUKOHARJO"},{"id":35159,"name":"KARANGANYAR","provinceId":32676,"provinceName":"JAWA TENGAH","regencyId":34900,"regencyName":"WONOSOBO","districtId":35154,"districtName":"SUKOHARJO"},{"id":35160,"name":"SEMPOL","provinceId":32676,"provinceName":"JAWA TENGAH","regencyId":34900,"regencyName":"WONOSOBO","districtId":35154,"districtName":"SUKOHARJO"},{"id":35161,"name":"PLODONGAN","provinceId":32676,"provinceName":"JAWA TENGAH","regencyId":34900,"regencyName":"WONOSOBO","districtId":35154,"districtName":"SUKOHARJO"},{"id":35162,"name":"SUROYUDAN","provinceId":32676,"provinceName":"JAWA TENGAH","regencyId":34900,"regencyName":"WONOSOBO","districtId":35154,"districtName":"SUKOHARJO"},{"id":35163,"name":"GUMIWANG","provinceId":32676,"provinceName":"JAWA TENGAH","regencyId":34900,"regencyName":"WONOSOBO","districtId":35154,"districtName":"SUKOHARJO"},{"id":35164,"name":"GUNUNGTUGEL","provinceId":32676,"provinceName":"JAWA TENGAH","regencyId":34900,"regencyName":"WONOSOBO","districtId":35154,"districtName":"SUKOHARJO"},{"id":35165,"name":"PULUS","provinceId":32676,"provinceName":"JAWA TENGAH","regencyId":34900,"regencyName":"WONOSOBO","districtId":35154,"districtName":"SUKOHARJO"},{"id":35166,"name":"PUCUNGWETAN","provinceId":32676,"provinceName":"JAWA TENGAH","regencyId":34900,"regencyName":"WONOSOBO","districtId":35154,"districtName":"SUKOHARJO"},{"id":35167,"name":"KAJEKSAN","provinceId":32676,"provinceName":"JAWA TENGAH","regencyId":34900,"regencyName":"WONOSOBO","districtId":35154,"districtName":"SUKOHARJO"},{"id":35168,"name":"TLOGO","provinceId":32676,"provinceName":"JAWA TENGAH","regencyId":34900,"regencyName":"WONOSOBO","districtId":35154,"districtName":"SUKOHARJO"},{"id":35169,"name":"KALIBENING","provinceId":32676,"provinceName":"JAWA TENGAH","regencyId":34900,"regencyName":"WONOSOBO","districtId":35154,"districtName":"SUKOHARJO"},{"id":35170,"name":"GARUNGLOR","provinceId":32676,"provinceName":"JAWA TENGAH","regencyId":34900,"regencyName":"WONOSOBO","districtId":35154,"districtName":"SUKOHARJO"},{"id":35171,"name":"JEBENGPLAMPITAN","provinceId":32676,"provinceName":"JAWA TENGAH","regencyId":34900,"regencyName":"WONOSOBO","districtId":35154,"districtName":"SUKOHARJO"}]}