{"status":"ok","data":{"regionNames":["IDN","JAWA TIMUR","KOTA PASURUAN","PANGGUNGREJO","MAYANGAN"],"regionIds":[0,42385,51268,83540,51290],"ts":1556222788,"tpsDiffCount":0,"tpsCount":8,"votes":{"01":{"kpu":822,"kawalPemilu":822},"02":{"kpu":721,"kawalPemilu":721}},"childs":{"1":{"name":"001","ts":1556222788,"votes":{"01":{"kpu":100,"kawalPemilu":100},"02":{"kpu":75,"kawalPemilu":75}}},"2":{"name":"002","ts":1556222788,"votes":{"01":{"kpu":104,"kawalPemilu":104},"02":{"kpu":84,"kawalPemilu":84}}},"3":{"name":"003","ts":1556222788,"votes":{"01":{"kpu":92,"kawalPemilu":92},"02":{"kpu":107,"kawalPemilu":107}}},"4":{"name":"004","ts":1556222788,"votes":{"01":{"kpu":116,"kawalPemilu":116},"02":{"kpu":111,"kawalPemilu":111}}},"5":{"name":"005","ts":1556222788,"votes":{"01":{"kpu":118,"kawalPemilu":118},"02":{"kpu":80,"kawalPemilu":80}}},"6":{"name":"006","ts":1556222788,"votes":{"01":{"kpu":108,"kawalPemilu":108},"02":{"kpu":57,"kawalPemilu":57}}},"7":{"name":"007","ts":1556222788,"votes":{"01":{"kpu":86,"kawalPemilu":86},"02":{"kpu":112,"kawalPemilu":112}}},"8":{"name":"008","ts":1556222788,"votes":{"01":{"kpu":98,"kawalPemilu":98},"02":{"kpu":95,"kawalPemilu":95}}}}}}