{"status":"ok","data":[{"id":37793,"name":"GOMBANG","provinceId":32676,"provinceName":"JAWA TENGAH","regencyId":37514,"regencyName":"BLORA","districtId":37792,"districtName":"BOGOREJO"},{"id":37794,"name":"SARIREJO","provinceId":32676,"provinceName":"JAWA TENGAH","regencyId":37514,"regencyName":"BLORA","districtId":37792,"districtName":"BOGOREJO"},{"id":37795,"name":"KARANGANYAR","provinceId":32676,"provinceName":"JAWA TENGAH","regencyId":37514,"regencyName":"BLORA","districtId":37792,"districtName":"BOGOREJO"},{"id":37796,"name":"KARANG","provinceId":32676,"provinceName":"JAWA TENGAH","regencyId":37514,"regencyName":"BLORA","districtId":37792,"districtName":"BOGOREJO"},{"id":37797,"name":"PRANTAAN","provinceId":32676,"provinceName":"JAWA TENGAH","regencyId":37514,"regencyName":"BLORA","districtId":37792,"districtName":"BOGOREJO"},{"id":37798,"name":"JERUK","provinceId":32676,"provinceName":"JAWA TENGAH","regencyId":37514,"regencyName":"BLORA","districtId":37792,"districtName":"BOGOREJO"},{"id":37799,"name":"BOGOREJO","provinceId":32676,"provinceName":"JAWA TENGAH","regencyId":37514,"regencyName":"BLORA","districtId":37792,"districtName":"BOGOREJO"},{"id":37800,"name":"GEMBOL","provinceId":32676,"provinceName":"JAWA TENGAH","regencyId":37514,"regencyName":"BLORA","districtId":37792,"districtName":"BOGOREJO"},{"id":37801,"name":"TEMPUREJO","provinceId":32676,"provinceName":"JAWA TENGAH","regencyId":37514,"regencyName":"BLORA","districtId":37792,"districtName":"BOGOREJO"},{"id":37802,"name":"GAYAM","provinceId":32676,"provinceName":"JAWA TENGAH","regencyId":37514,"regencyName":"BLORA","districtId":37792,"districtName":"BOGOREJO"},{"id":37803,"name":"SENDANGREJO","provinceId":32676,"provinceName":"JAWA TENGAH","regencyId":37514,"regencyName":"BLORA","districtId":37792,"districtName":"BOGOREJO"},{"id":37804,"name":"GANDU","provinceId":32676,"provinceName":"JAWA TENGAH","regencyId":37514,"regencyName":"BLORA","districtId":37792,"districtName":"BOGOREJO"},{"id":37805,"name":"NGLENGKIR","provinceId":32676,"provinceName":"JAWA TENGAH","regencyId":37514,"regencyName":"BLORA","districtId":37792,"districtName":"BOGOREJO"},{"id":37806,"name":"JURANGJERO","provinceId":32676,"provinceName":"JAWA TENGAH","regencyId":37514,"regencyName":"BLORA","districtId":37792,"districtName":"BOGOREJO"}]}