{"status":"ok","data":[{"id":57194,"name":"MAKAMENGGIT","provinceId":55065,"provinceName":"NUSA TENGGARA TIMUR","regencyId":57167,"regencyName":"SUMBA TIMUR","districtId":57193,"districtName":"NGGAHA ORI ANGU"},{"id":57195,"name":"TANDULA JANGGA","provinceId":55065,"provinceName":"NUSA TENGGARA TIMUR","regencyId":57167,"regencyName":"SUMBA TIMUR","districtId":57193,"districtName":"NGGAHA ORI ANGU"},{"id":57196,"name":"PRAI PAHA","provinceId":55065,"provinceName":"NUSA TENGGARA TIMUR","regencyId":57167,"regencyName":"SUMBA TIMUR","districtId":57193,"districtName":"NGGAHA ORI ANGU"},{"id":57197,"name":"PRAIHAMBULI","provinceId":55065,"provinceName":"NUSA TENGGARA TIMUR","regencyId":57167,"regencyName":"SUMBA TIMUR","districtId":57193,"districtName":"NGGAHA ORI ANGU"},{"id":57198,"name":"PULU PANJANG","provinceId":55065,"provinceName":"NUSA TENGGARA TIMUR","regencyId":57167,"regencyName":"SUMBA TIMUR","districtId":57193,"districtName":"NGGAHA ORI ANGU"},{"id":57199,"name":"PRAIKARANG","provinceId":55065,"provinceName":"NUSA TENGGARA TIMUR","regencyId":57167,"regencyName":"SUMBA TIMUR","districtId":57193,"districtName":"NGGAHA ORI ANGU"},{"id":57200,"name":"TANA TUKU","provinceId":55065,"provinceName":"NUSA TENGGARA TIMUR","regencyId":57167,"regencyName":"SUMBA TIMUR","districtId":57193,"districtName":"NGGAHA ORI ANGU"},{"id":57201,"name":"NGADU LANGGI","provinceId":55065,"provinceName":"NUSA TENGGARA TIMUR","regencyId":57167,"regencyName":"SUMBA TIMUR","districtId":57193,"districtName":"NGGAHA ORI ANGU"}]}