{"status":"ok","data":[{"id":42034,"name":"WONOKROMO","provinceId":41863,"provinceName":"DAERAH ISTIMEWA YOGYAKARTA","regencyId":41965,"regencyName":"BANTUL","districtId":42033,"districtName":"PLERET"},{"id":42035,"name":"PLERET","provinceId":41863,"provinceName":"DAERAH ISTIMEWA YOGYAKARTA","regencyId":41965,"regencyName":"BANTUL","districtId":42033,"districtName":"PLERET"},{"id":42036,"name":"SEGOROYOSO","provinceId":41863,"provinceName":"DAERAH ISTIMEWA YOGYAKARTA","regencyId":41965,"regencyName":"BANTUL","districtId":42033,"districtName":"PLERET"},{"id":42037,"name":"BAWURAN","provinceId":41863,"provinceName":"DAERAH ISTIMEWA YOGYAKARTA","regencyId":41965,"regencyName":"BANTUL","districtId":42033,"districtName":"PLERET"},{"id":42038,"name":"WONOLELO","provinceId":41863,"provinceName":"DAERAH ISTIMEWA YOGYAKARTA","regencyId":41965,"regencyName":"BANTUL","districtId":42033,"districtName":"PLERET"}]}