{"status":"ok","data":{"regionNames":["IDN","KALIMANTAN BARAT","SAMBAS","JAWAI","PELIMPAAN"],"regionIds":[0,58285,58286,58331,58337],"ts":1556230118,"tpsDiffCount":0,"tpsCount":8,"votes":{"01":{"kpu":556,"kawalPemilu":556},"02":{"kpu":696,"kawalPemilu":696}},"childs":{"1":{"name":"001","ts":1556230118,"votes":{"01":{"kpu":117,"kawalPemilu":117},"02":{"kpu":56,"kawalPemilu":56}}},"2":{"name":"002","ts":1556230118,"votes":{"01":{"kpu":102,"kawalPemilu":102},"02":{"kpu":75,"kawalPemilu":75}}},"3":{"name":"003","ts":1556230118,"votes":{"01":{"kpu":75,"kawalPemilu":75},"02":{"kpu":97,"kawalPemilu":97}}},"4":{"name":"004","ts":1556230118,"votes":{"01":{"kpu":64,"kawalPemilu":64},"02":{"kpu":96,"kawalPemilu":96}}},"5":{"name":"005","ts":1556230118,"votes":{"01":{"kpu":47,"kawalPemilu":47},"02":{"kpu":116,"kawalPemilu":116}}},"6":{"name":"006","ts":1556230118,"votes":{"01":{"kpu":33,"kawalPemilu":33},"02":{"kpu":83,"kawalPemilu":83}}},"7":{"name":"007","ts":1556230118,"votes":{"01":{"kpu":45,"kawalPemilu":45},"02":{"kpu":99,"kawalPemilu":99}}},"8":{"name":"008","ts":1556230118,"votes":{"01":{"kpu":73,"kawalPemilu":73},"02":{"kpu":74,"kawalPemilu":74}}}}}}