{"status":"ok","data":[{"id":76749,"name":"KOTA SIRIH","provinceId":76096,"provinceName":"MALUKU","regencyId":76708,"regencyName":"SERAM BAGIAN TIMUR","districtId":83831,"districtName":"GOROM TIMUR"},{"id":76750,"name":"KILKODA","provinceId":76096,"provinceName":"MALUKU","regencyId":76708,"regencyName":"SERAM BAGIAN TIMUR","districtId":83831,"districtName":"GOROM TIMUR"},{"id":76751,"name":"MIRAN","provinceId":76096,"provinceName":"MALUKU","regencyId":76708,"regencyName":"SERAM BAGIAN TIMUR","districtId":83831,"districtName":"GOROM TIMUR"},{"id":76752,"name":"RARAT","provinceId":76096,"provinceName":"MALUKU","regencyId":76708,"regencyName":"SERAM BAGIAN TIMUR","districtId":83831,"districtName":"GOROM TIMUR"},{"id":86061,"name":"ARAN","provinceId":76096,"provinceName":"MALUKU","regencyId":76708,"regencyName":"SERAM BAGIAN TIMUR","districtId":83831,"districtName":"GOROM TIMUR"},{"id":86062,"name":"BAS","provinceId":76096,"provinceName":"MALUKU","regencyId":76708,"regencyName":"SERAM BAGIAN TIMUR","districtId":83831,"districtName":"GOROM TIMUR"},{"id":86063,"name":"TUNAS ILUR","provinceId":76096,"provinceName":"MALUKU","regencyId":76708,"regencyName":"SERAM BAGIAN TIMUR","districtId":83831,"districtName":"GOROM TIMUR"},{"id":86064,"name":"SAGEY","provinceId":76096,"provinceName":"MALUKU","regencyId":76708,"regencyName":"SERAM BAGIAN TIMUR","districtId":83831,"districtName":"GOROM TIMUR"},{"id":86065,"name":"ARMADA","provinceId":76096,"provinceName":"MALUKU","regencyId":76708,"regencyName":"SERAM BAGIAN TIMUR","districtId":83831,"districtName":"GOROM TIMUR"},{"id":86066,"name":"WAISALAN","provinceId":76096,"provinceName":"MALUKU","regencyId":76708,"regencyName":"SERAM BAGIAN TIMUR","districtId":83831,"districtName":"GOROM TIMUR"},{"id":86067,"name":"BASARIN","provinceId":76096,"provinceName":"MALUKU","regencyId":76708,"regencyName":"SERAM BAGIAN TIMUR","districtId":83831,"districtName":"GOROM TIMUR"},{"id":86068,"name":"GOHA","provinceId":76096,"provinceName":"MALUKU","regencyId":76708,"regencyName":"SERAM BAGIAN TIMUR","districtId":83831,"districtName":"GOROM TIMUR"},{"id":86069,"name":"ADAR","provinceId":76096,"provinceName":"MALUKU","regencyId":76708,"regencyName":"SERAM BAGIAN TIMUR","districtId":83831,"districtName":"GOROM TIMUR"},{"id":86070,"name":"TINARIN","provinceId":76096,"provinceName":"MALUKU","regencyId":76708,"regencyName":"SERAM BAGIAN TIMUR","districtId":83831,"districtName":"GOROM TIMUR"},{"id":91182,"name":"AMARWATU","provinceId":76096,"provinceName":"MALUKU","regencyId":76708,"regencyName":"SERAM BAGIAN TIMUR","districtId":83831,"districtName":"GOROM TIMUR"},{"id":91183,"name":"TUHA","provinceId":76096,"provinceName":"MALUKU","regencyId":76708,"regencyName":"SERAM BAGIAN TIMUR","districtId":83831,"districtName":"GOROM TIMUR"},{"id":91220,"name":"MIRAN GOTA","provinceId":76096,"provinceName":"MALUKU","regencyId":76708,"regencyName":"SERAM BAGIAN TIMUR","districtId":83831,"districtName":"GOROM TIMUR"},{"id":928834,"name":"ETARALU","provinceId":76096,"provinceName":"MALUKU","regencyId":76708,"regencyName":"SERAM BAGIAN TIMUR","districtId":83831,"districtName":"GOROM TIMUR"},{"id":928835,"name":"KILTUFA","provinceId":76096,"provinceName":"MALUKU","regencyId":76708,"regencyName":"SERAM BAGIAN TIMUR","districtId":83831,"districtName":"GOROM TIMUR"},{"id":928836,"name":"MIRAN KILIAN","provinceId":76096,"provinceName":"MALUKU","regencyId":76708,"regencyName":"SERAM BAGIAN TIMUR","districtId":83831,"districtName":"GOROM TIMUR"},{"id":928837,"name":"MIRAN KELEDAR","provinceId":76096,"provinceName":"MALUKU","regencyId":76708,"regencyName":"SERAM BAGIAN TIMUR","districtId":83831,"districtName":"GOROM TIMUR"},{"id":928838,"name":"MIRAN MANABAN","provinceId":76096,"provinceName":"MALUKU","regencyId":76708,"regencyName":"SERAM BAGIAN TIMUR","districtId":83831,"districtName":"GOROM TIMUR"},{"id":928839,"name":"MIRAN RUMUAR","provinceId":76096,"provinceName":"MALUKU","regencyId":76708,"regencyName":"SERAM BAGIAN TIMUR","districtId":83831,"districtName":"GOROM TIMUR"}]}