{"status":"ok","data":{"regionNames":["IDN","NUSA TENGGARA TIMUR","KUPANG","AMARASI BARAT","NIUKBAUN"],"regionIds":[0,55065,55066,55250,55254],"ts":1556227832,"tpsDiffCount":0,"tpsCount":3,"votes":{"01":{"kpu":558,"kawalPemilu":558},"02":{"kpu":39,"kawalPemilu":39}},"childs":{"2":{"name":"002","ts":1556227832,"votes":{"01":{"kpu":180,"kawalPemilu":180},"02":{"kpu":14,"kawalPemilu":14}}},"3":{"name":"003","ts":1556227832,"votes":{"01":{"kpu":193,"kawalPemilu":193},"02":{"kpu":18,"kawalPemilu":18}}},"4":{"name":"004","ts":1556227832,"votes":{"01":{"kpu":185,"kawalPemilu":185},"02":{"kpu":7,"kawalPemilu":7}}}}}}