{"status":"ok","data":{"regionNames":["IDN","KALIMANTAN BARAT","KETAPANG","BENUA KAYONG","MULIA KERTA"],"regionIds":[0,58285,58749,58931,58933],"ts":1556230687,"tpsDiffCount":1,"tpsCount":18,"votes":{"01":{"kpu":466,"kawalPemilu":466},"02":{"kpu":3419,"kawalPemilu":3418}},"childs":{"1":{"name":"001","ts":1556230687,"votes":{"01":{"kpu":39,"kawalPemilu":39},"02":{"kpu":204,"kawalPemilu":204}}},"2":{"name":"002","ts":1556230687,"votes":{"01":{"kpu":47,"kawalPemilu":47},"02":{"kpu":206,"kawalPemilu":206}}},"8":{"name":"008","ts":1556230687,"votes":{"01":{"kpu":49,"kawalPemilu":49},"02":{"kpu":192,"kawalPemilu":192}}},"11":{"name":"011","ts":1556230687,"votes":{"01":{"kpu":19,"kawalPemilu":19},"02":{"kpu":203,"kawalPemilu":203}}},"19":{"name":"019","ts":1556230687,"votes":{"01":{"kpu":31,"kawalPemilu":31},"02":{"kpu":136,"kawalPemilu":135}}},"3":{"name":"003","ts":1556230687,"votes":{"01":{"kpu":48,"kawalPemilu":48},"02":{"kpu":226,"kawalPemilu":226}}},"5":{"name":"005","ts":1556230687,"votes":{"01":{"kpu":11,"kawalPemilu":11},"02":{"kpu":243,"kawalPemilu":243}}},"6":{"name":"006","ts":1556230687,"votes":{"01":{"kpu":37,"kawalPemilu":37},"02":{"kpu":191,"kawalPemilu":191}}},"10":{"name":"010","ts":1556230687,"votes":{"01":{"kpu":9,"kawalPemilu":9},"02":{"kpu":209,"kawalPemilu":209}}},"12":{"name":"012","ts":1556230687,"votes":{"01":{"kpu":23,"kawalPemilu":23},"02":{"kpu":197,"kawalPemilu":197}}},"13":{"name":"013","ts":1556230687,"votes":{"01":{"kpu":14,"kawalPemilu":14},"02":{"kpu":222,"kawalPemilu":222}}},"14":{"name":"014","ts":1556230687,"votes":{"01":{"kpu":18,"kawalPemilu":18},"02":{"kpu":237,"kawalPemilu":237}}},"15":{"name":"015","ts":1556230687,"votes":{"01":{"kpu":16,"kawalPemilu":16},"02":{"kpu":166,"kawalPemilu":166}}},"18":{"name":"018","ts":1556230687,"votes":{"01":{"kpu":8,"kawalPemilu":8},"02":{"kpu":151,"kawalPemilu":151}}},"20":{"name":"020","ts":1556230687,"votes":{"01":{"kpu":36,"kawalPemilu":36},"02":{"kpu":98,"kawalPemilu":98}}},"21":{"name":"021","ts":1556230687,"votes":{"01":{"kpu":17,"kawalPemilu":17},"02":{"kpu":157,"kawalPemilu":157}}},"22":{"name":"022","ts":1556230687,"votes":{"01":{"kpu":16,"kawalPemilu":16},"02":{"kpu":186,"kawalPemilu":186}}},"23":{"name":"023","ts":1556230687,"votes":{"01":{"kpu":28,"kawalPemilu":28},"02":{"kpu":195,"kawalPemilu":195}}}}}}