{"status":"ok","data":{"regionNames":["IDN","KALIMANTAN TIMUR","PASER","BATU SOPANG"],"regionIds":[0,64111,64112,64113],"ts":1556235334,"tpsDiffCount":0,"tpsCount":19,"votes":{"01":{"kpu":1628,"kawalPemilu":1628},"02":{"kpu":1738,"kawalPemilu":1738}},"childs":{"64115":{"id":64115,"name":"BUSUI","ts":1556235329,"tpsCount":5,"tpsDiffCount":0,"votes":{"01":{"kpu":363,"kawalPemilu":363},"02":{"kpu":456,"kawalPemilu":456}}},"64116":{"id":64116,"name":"BATU KAJANG","ts":1556235332,"tpsCount":11,"tpsDiffCount":0,"votes":{"01":{"kpu":976,"kawalPemilu":976},"02":{"kpu":1074,"kawalPemilu":1074}}},"64118":{"id":64118,"name":"SUNGAI TERIK","ts":1556235334,"tpsCount":3,"tpsDiffCount":0,"votes":{"01":{"kpu":289,"kawalPemilu":289},"02":{"kpu":208,"kawalPemilu":208}}}}}}