{"status":"ok","data":[{"id":87042,"name":"MULI","provinceId":78203,"provinceName":"PAPUA","regencyId":79629,"regencyName":"NDUGA","districtId":83750,"districtName":"WUTPAGA"},{"id":87043,"name":"TINIGELE","provinceId":78203,"provinceName":"PAPUA","regencyId":79629,"regencyName":"NDUGA","districtId":83750,"districtName":"WUTPAGA"},{"id":87044,"name":"WUONE","provinceId":78203,"provinceName":"PAPUA","regencyId":79629,"regencyName":"NDUGA","districtId":83750,"districtName":"WUTPAGA"},{"id":87045,"name":"LUAREN","provinceId":78203,"provinceName":"PAPUA","regencyId":79629,"regencyName":"NDUGA","districtId":83750,"districtName":"WUTPAGA"},{"id":89179,"name":"WANGUN","provinceId":78203,"provinceName":"PAPUA","regencyId":79629,"regencyName":"NDUGA","districtId":83750,"districtName":"WUTPAGA"},{"id":89180,"name":"WUTPAGA","provinceId":78203,"provinceName":"PAPUA","regencyId":79629,"regencyName":"NDUGA","districtId":83750,"districtName":"WUTPAGA"}]}