{"status":"ok","data":{"regionNames":["IDN","SUMATERA UTARA","KOTA PEMATANGSIANTAR","SIANTAR MARIMBUN","TONG MARIMBUN"],"regionIds":[0,6728,11916,11971,11973],"ts":1556178890,"tpsDiffCount":0,"tpsCount":6,"votes":{"01":{"kpu":1200,"kawalPemilu":1200},"02":{"kpu":30,"kawalPemilu":30}},"childs":{"2":{"name":"002","ts":1556178890,"votes":{"01":{"kpu":159,"kawalPemilu":159},"02":{"kpu":4,"kawalPemilu":4}}},"3":{"name":"003","ts":1556178890,"votes":{"01":{"kpu":214,"kawalPemilu":214},"02":{"kpu":8,"kawalPemilu":8}}},"4":{"name":"004","ts":1556178890,"votes":{"01":{"kpu":144,"kawalPemilu":144},"02":{"kpu":1,"kawalPemilu":1}}},"5":{"name":"005","ts":1556178890,"votes":{"01":{"kpu":236,"kawalPemilu":236},"02":{"kpu":6,"kawalPemilu":6}}},"6":{"name":"006","ts":1556178890,"votes":{"01":{"kpu":195,"kawalPemilu":195},"02":{"kpu":1,"kawalPemilu":1}}},"7":{"name":"007","ts":1556178890,"votes":{"01":{"kpu":252,"kawalPemilu":252},"02":{"kpu":10,"kawalPemilu":10}}}}}}