{"status":"ok","data":[{"id":59455,"name":"BADAU","provinceId":58285,"provinceName":"KALIMANTAN BARAT","regencyId":59320,"regencyName":"KAPUAS HULU","districtId":59454,"districtName":"BADAU"},{"id":59456,"name":"JANTING","provinceId":58285,"provinceName":"KALIMANTAN BARAT","regencyId":59320,"regencyName":"KAPUAS HULU","districtId":59454,"districtName":"BADAU"},{"id":59457,"name":"SEMUNTIK","provinceId":58285,"provinceName":"KALIMANTAN BARAT","regencyId":59320,"regencyName":"KAPUAS HULU","districtId":59454,"districtName":"BADAU"},{"id":59458,"name":"KEKURAK","provinceId":58285,"provinceName":"KALIMANTAN BARAT","regencyId":59320,"regencyName":"KAPUAS HULU","districtId":59454,"districtName":"BADAU"},{"id":59459,"name":"PULAU MAJANG","provinceId":58285,"provinceName":"KALIMANTAN BARAT","regencyId":59320,"regencyName":"KAPUAS HULU","districtId":59454,"districtName":"BADAU"},{"id":59460,"name":"SERIANG","provinceId":58285,"provinceName":"KALIMANTAN BARAT","regencyId":59320,"regencyName":"KAPUAS HULU","districtId":59454,"districtName":"BADAU"},{"id":59461,"name":"TINTING SELIGI","provinceId":58285,"provinceName":"KALIMANTAN BARAT","regencyId":59320,"regencyName":"KAPUAS HULU","districtId":59454,"districtName":"BADAU"},{"id":59462,"name":"SEBINDANG","provinceId":58285,"provinceName":"KALIMANTAN BARAT","regencyId":59320,"regencyName":"KAPUAS HULU","districtId":59454,"districtName":"BADAU"},{"id":59463,"name":"TAJUM","provinceId":58285,"provinceName":"KALIMANTAN BARAT","regencyId":59320,"regencyName":"KAPUAS HULU","districtId":59454,"districtName":"BADAU"}]}