{"status":"ok","data":[{"id":6629,"name":"PONDOK KEMUNING","provinceId":1,"provinceName":"ACEH","regencyId":6591,"regencyName":"KOTA LANGSA","districtId":6628,"districtName":"LANGSA LAMA"},{"id":6630,"name":"SEULALAH","provinceId":1,"provinceName":"ACEH","regencyId":6591,"regencyName":"KOTA LANGSA","districtId":6628,"districtName":"LANGSA LAMA"},{"id":6631,"name":"PONDOK PABRIK","provinceId":1,"provinceName":"ACEH","regencyId":6591,"regencyName":"KOTA LANGSA","districtId":6628,"districtName":"LANGSA LAMA"},{"id":6632,"name":"SIDODADI","provinceId":1,"provinceName":"ACEH","regencyId":6591,"regencyName":"KOTA LANGSA","districtId":6628,"districtName":"LANGSA LAMA"},{"id":6633,"name":"SIDOREJO","provinceId":1,"provinceName":"ACEH","regencyId":6591,"regencyName":"KOTA LANGSA","districtId":6628,"districtName":"LANGSA LAMA"},{"id":6634,"name":"BARO","provinceId":1,"provinceName":"ACEH","regencyId":6591,"regencyName":"KOTA LANGSA","districtId":6628,"districtName":"LANGSA LAMA"},{"id":6635,"name":"MEURANDEH","provinceId":1,"provinceName":"ACEH","regencyId":6591,"regencyName":"KOTA LANGSA","districtId":6628,"districtName":"LANGSA LAMA"},{"id":6636,"name":"ASAM PEUTIK","provinceId":1,"provinceName":"ACEH","regencyId":6591,"regencyName":"KOTA LANGSA","districtId":6628,"districtName":"LANGSA LAMA"},{"id":6637,"name":"BAROH LANGSA LAMA","provinceId":1,"provinceName":"ACEH","regencyId":6591,"regencyName":"KOTA LANGSA","districtId":6628,"districtName":"LANGSA LAMA"},{"id":88074,"name":"SEULALAH BARU","provinceId":1,"provinceName":"ACEH","regencyId":6591,"regencyName":"KOTA LANGSA","districtId":6628,"districtName":"LANGSA LAMA"},{"id":88075,"name":"SUKA JADI KEBUN IRENG","provinceId":1,"provinceName":"ACEH","regencyId":6591,"regencyName":"KOTA LANGSA","districtId":6628,"districtName":"LANGSA LAMA"},{"id":88076,"name":"MEURANDEH TEUNGOH","provinceId":1,"provinceName":"ACEH","regencyId":6591,"regencyName":"KOTA LANGSA","districtId":6628,"districtName":"LANGSA LAMA"},{"id":88077,"name":"MEURANDEH DAYAH","provinceId":1,"provinceName":"ACEH","regencyId":6591,"regencyName":"KOTA LANGSA","districtId":6628,"districtName":"LANGSA LAMA"},{"id":88078,"name":"MEURANDEH ACEH","provinceId":1,"provinceName":"ACEH","regencyId":6591,"regencyName":"KOTA LANGSA","districtId":6628,"districtName":"LANGSA LAMA"},{"id":88079,"name":"BATE PUTEH","provinceId":1,"provinceName":"ACEH","regencyId":6591,"regencyName":"KOTA LANGSA","districtId":6628,"districtName":"LANGSA LAMA"}]}