{"status":"ok","data":[{"id":29900,"name":"SAGARA","provinceId":26141,"provinceName":"JAWA BARAT","regencyId":29834,"regencyName":"MAJALENGKA","districtId":29899,"districtName":"ARGAPURA"},{"id":29901,"name":"CIBUNUT","provinceId":26141,"provinceName":"JAWA BARAT","regencyId":29834,"regencyName":"MAJALENGKA","districtId":29899,"districtName":"ARGAPURA"},{"id":29902,"name":"TEJAMULYA","provinceId":26141,"provinceName":"JAWA BARAT","regencyId":29834,"regencyName":"MAJALENGKA","districtId":29899,"districtName":"ARGAPURA"},{"id":29903,"name":"SUKASARI KALER","provinceId":26141,"provinceName":"JAWA BARAT","regencyId":29834,"regencyName":"MAJALENGKA","districtId":29899,"districtName":"ARGAPURA"},{"id":29904,"name":"ARGAMUKTI","provinceId":26141,"provinceName":"JAWA BARAT","regencyId":29834,"regencyName":"MAJALENGKA","districtId":29899,"districtName":"ARGAPURA"},{"id":29905,"name":"SUKADANA","provinceId":26141,"provinceName":"JAWA BARAT","regencyId":29834,"regencyName":"MAJALENGKA","districtId":29899,"districtName":"ARGAPURA"},{"id":29906,"name":"SADASARI","provinceId":26141,"provinceName":"JAWA BARAT","regencyId":29834,"regencyName":"MAJALENGKA","districtId":29899,"districtName":"ARGAPURA"},{"id":29907,"name":"HAURSEAH","provinceId":26141,"provinceName":"JAWA BARAT","regencyId":29834,"regencyName":"MAJALENGKA","districtId":29899,"districtName":"ARGAPURA"},{"id":29908,"name":"MEKARWANGI","provinceId":26141,"provinceName":"JAWA BARAT","regencyId":29834,"regencyName":"MAJALENGKA","districtId":29899,"districtName":"ARGAPURA"},{"id":29909,"name":"CIKARACAK","provinceId":26141,"provinceName":"JAWA BARAT","regencyId":29834,"regencyName":"MAJALENGKA","districtId":29899,"districtName":"ARGAPURA"},{"id":29910,"name":"HEUBEUL ISUK","provinceId":26141,"provinceName":"JAWA BARAT","regencyId":29834,"regencyName":"MAJALENGKA","districtId":29899,"districtName":"ARGAPURA"},{"id":29911,"name":"SUKASARI KIDUL","provinceId":26141,"provinceName":"JAWA BARAT","regencyId":29834,"regencyName":"MAJALENGKA","districtId":29899,"districtName":"ARGAPURA"},{"id":29912,"name":"GUNUNGWANGI","provinceId":26141,"provinceName":"JAWA BARAT","regencyId":29834,"regencyName":"MAJALENGKA","districtId":29899,"districtName":"ARGAPURA"},{"id":29913,"name":"ARGALINGGA","provinceId":26141,"provinceName":"JAWA BARAT","regencyId":29834,"regencyName":"MAJALENGKA","districtId":29899,"districtName":"ARGAPURA"}]}