{"status":"ok","data":[{"id":34920,"name":"GONDOWULAN","provinceId":32676,"provinceName":"JAWA TENGAH","regencyId":34900,"regencyName":"WONOSOBO","districtId":34919,"districtName":"KEPIL"},{"id":34921,"name":"JANGKRIKAN","provinceId":32676,"provinceName":"JAWA TENGAH","regencyId":34900,"regencyName":"WONOSOBO","districtId":34919,"districtName":"KEPIL"},{"id":34922,"name":"TEGESWETAN","provinceId":32676,"provinceName":"JAWA TENGAH","regencyId":34900,"regencyName":"WONOSOBO","districtId":34919,"districtName":"KEPIL"},{"id":34923,"name":"GADINGSUKUH","provinceId":32676,"provinceName":"JAWA TENGAH","regencyId":34900,"regencyName":"WONOSOBO","districtId":34919,"districtName":"KEPIL"},{"id":34924,"name":"BURAT","provinceId":32676,"provinceName":"JAWA TENGAH","regencyId":34900,"regencyName":"WONOSOBO","districtId":34919,"districtName":"KEPIL"},{"id":34925,"name":"BENER","provinceId":32676,"provinceName":"JAWA TENGAH","regencyId":34900,"regencyName":"WONOSOBO","districtId":34919,"districtName":"KEPIL"},{"id":34926,"name":"GADINGREJO","provinceId":32676,"provinceName":"JAWA TENGAH","regencyId":34900,"regencyName":"WONOSOBO","districtId":34919,"districtName":"KEPIL"},{"id":34927,"name":"KEPIL","provinceId":32676,"provinceName":"JAWA TENGAH","regencyId":34900,"regencyName":"WONOSOBO","districtId":34919,"districtName":"KEPIL"},{"id":34928,"name":"BERAN","provinceId":32676,"provinceName":"JAWA TENGAH","regencyId":34900,"regencyName":"WONOSOBO","districtId":34919,"districtName":"KEPIL"},{"id":34929,"name":"KAPULOGO","provinceId":32676,"provinceName":"JAWA TENGAH","regencyId":34900,"regencyName":"WONOSOBO","districtId":34919,"districtName":"KEPIL"},{"id":34930,"name":"KAGUNGAN","provinceId":32676,"provinceName":"JAWA TENGAH","regencyId":34900,"regencyName":"WONOSOBO","districtId":34919,"districtName":"KEPIL"},{"id":34931,"name":"RANDUSARI","provinceId":32676,"provinceName":"JAWA TENGAH","regencyId":34900,"regencyName":"WONOSOBO","districtId":34919,"districtName":"KEPIL"},{"id":34932,"name":"REJOSARI","provinceId":32676,"provinceName":"JAWA TENGAH","regencyId":34900,"regencyName":"WONOSOBO","districtId":34919,"districtName":"KEPIL"},{"id":34933,"name":"NGALIAN","provinceId":32676,"provinceName":"JAWA TENGAH","regencyId":34900,"regencyName":"WONOSOBO","districtId":34919,"districtName":"KEPIL"},{"id":34934,"name":"KALIPURU","provinceId":32676,"provinceName":"JAWA TENGAH","regencyId":34900,"regencyName":"WONOSOBO","districtId":34919,"districtName":"KEPIL"},{"id":34935,"name":"TANJUNGANOM","provinceId":32676,"provinceName":"JAWA TENGAH","regencyId":34900,"regencyName":"WONOSOBO","districtId":34919,"districtName":"KEPIL"},{"id":34936,"name":"KALIWULUH","provinceId":32676,"provinceName":"JAWA TENGAH","regencyId":34900,"regencyName":"WONOSOBO","districtId":34919,"districtName":"KEPIL"},{"id":34937,"name":"TEGALGOT","provinceId":32676,"provinceName":"JAWA TENGAH","regencyId":34900,"regencyName":"WONOSOBO","districtId":34919,"districtName":"KEPIL"},{"id":34938,"name":"WARANGAN","provinceId":32676,"provinceName":"JAWA TENGAH","regencyId":34900,"regencyName":"WONOSOBO","districtId":34919,"districtName":"KEPIL"},{"id":34939,"name":"ROPOH","provinceId":32676,"provinceName":"JAWA TENGAH","regencyId":34900,"regencyName":"WONOSOBO","districtId":34919,"districtName":"KEPIL"},{"id":34940,"name":"PULOSAREN","provinceId":32676,"provinceName":"JAWA TENGAH","regencyId":34900,"regencyName":"WONOSOBO","districtId":34919,"districtName":"KEPIL"}]}