{"status":"ok","data":{"regionNames":["IDN","SUMATERA SELATAN","OGAN ILIR","INDRALAYA SELATAN","MERANJAT III"],"regionIds":[0,17404,20087,20223,20237],"ts":1556186709,"tpsDiffCount":0,"tpsCount":4,"votes":{"01":{"kpu":409,"kawalPemilu":409},"02":{"kpu":433,"kawalPemilu":433}},"childs":{"1":{"name":"001","ts":1556186709,"votes":{"01":{"kpu":99,"kawalPemilu":99},"02":{"kpu":80,"kawalPemilu":80}}},"2":{"name":"002","ts":1556186709,"votes":{"01":{"kpu":112,"kawalPemilu":112},"02":{"kpu":113,"kawalPemilu":113}}},"3":{"name":"003","ts":1556186709,"votes":{"01":{"kpu":99,"kawalPemilu":99},"02":{"kpu":111,"kawalPemilu":111}}},"4":{"name":"004","ts":1556186709,"votes":{"01":{"kpu":99,"kawalPemilu":99},"02":{"kpu":129,"kawalPemilu":129}}}}}}