{"status":"ok","data":[{"id":27170,"name":"SUKAGALIH","provinceId":26141,"provinceName":"JAWA BARAT","regencyId":27026,"regencyName":"CIANJUR","districtId":27169,"districtName":"CIKALONGKULON"},{"id":27171,"name":"GUDANG","provinceId":26141,"provinceName":"JAWA BARAT","regencyId":27026,"regencyName":"CIANJUR","districtId":27169,"districtName":"CIKALONGKULON"},{"id":27172,"name":"CINANGSI","provinceId":26141,"provinceName":"JAWA BARAT","regencyId":27026,"regencyName":"CIANJUR","districtId":27169,"districtName":"CIKALONGKULON"},{"id":27173,"name":"CIJAGANG","provinceId":26141,"provinceName":"JAWA BARAT","regencyId":27026,"regencyName":"CIANJUR","districtId":27169,"districtName":"CIKALONGKULON"},{"id":27174,"name":"MAJALAYA","provinceId":26141,"provinceName":"JAWA BARAT","regencyId":27026,"regencyName":"CIANJUR","districtId":27169,"districtName":"CIKALONGKULON"},{"id":27175,"name":"KAMURANG","provinceId":26141,"provinceName":"JAWA BARAT","regencyId":27026,"regencyName":"CIANJUR","districtId":27169,"districtName":"CIKALONGKULON"},{"id":27176,"name":"WARUDOYONG","provinceId":26141,"provinceName":"JAWA BARAT","regencyId":27026,"regencyName":"CIANJUR","districtId":27169,"districtName":"CIKALONGKULON"},{"id":27177,"name":"CIRAMAGIRANG","provinceId":26141,"provinceName":"JAWA BARAT","regencyId":27026,"regencyName":"CIANJUR","districtId":27169,"districtName":"CIKALONGKULON"},{"id":27178,"name":"MEKARJAYA","provinceId":26141,"provinceName":"JAWA BARAT","regencyId":27026,"regencyName":"CIANJUR","districtId":27169,"districtName":"CIKALONGKULON"},{"id":27179,"name":"SUKAMULYA","provinceId":26141,"provinceName":"JAWA BARAT","regencyId":27026,"regencyName":"CIANJUR","districtId":27169,"districtName":"CIKALONGKULON"},{"id":27180,"name":"PADAJAYA","provinceId":26141,"provinceName":"JAWA BARAT","regencyId":27026,"regencyName":"CIANJUR","districtId":27169,"districtName":"CIKALONGKULON"},{"id":27181,"name":"CIGUNUNGHERANG","provinceId":26141,"provinceName":"JAWA BARAT","regencyId":27026,"regencyName":"CIANJUR","districtId":27169,"districtName":"CIKALONGKULON"},{"id":27182,"name":"NEGLASARI","provinceId":26141,"provinceName":"JAWA BARAT","regencyId":27026,"regencyName":"CIANJUR","districtId":27169,"districtName":"CIKALONGKULON"},{"id":27183,"name":"MEKARGALIH","provinceId":26141,"provinceName":"JAWA BARAT","regencyId":27026,"regencyName":"CIANJUR","districtId":27169,"districtName":"CIKALONGKULON"},{"id":27184,"name":"LEMBAHSARI","provinceId":26141,"provinceName":"JAWA BARAT","regencyId":27026,"regencyName":"CIANJUR","districtId":27169,"districtName":"CIKALONGKULON"},{"id":27185,"name":"MENTENGSARI","provinceId":26141,"provinceName":"JAWA BARAT","regencyId":27026,"regencyName":"CIANJUR","districtId":27169,"districtName":"CIKALONGKULON"},{"id":27186,"name":"MEKARSARI","provinceId":26141,"provinceName":"JAWA BARAT","regencyId":27026,"regencyName":"CIANJUR","districtId":27169,"districtName":"CIKALONGKULON"},{"id":27187,"name":"MEKARMULYA","provinceId":26141,"provinceName":"JAWA BARAT","regencyId":27026,"regencyName":"CIANJUR","districtId":27169,"districtName":"CIKALONGKULON"}]}