{"status":"ok","data":{"regionNames":["IDN","JAWA TENGAH","PEMALANG","AMPELGADING"],"regionIds":[0,32676,40622,40797],"ts":1556211529,"tpsDiffCount":1,"tpsCount":66,"votes":{"01":{"kpu":8647,"kawalPemilu":8648},"02":{"kpu":2275,"kawalPemilu":2272}},"childs":{"40805":{"id":40805,"name":"CIBIYUK","ts":1556211517,"tpsCount":7,"tpsDiffCount":0,"votes":{"01":{"kpu":963,"kawalPemilu":963},"02":{"kpu":252,"kawalPemilu":252}}},"40806":{"id":40806,"name":"KARANGTENGAH","ts":1556211518,"tpsCount":5,"tpsDiffCount":0,"votes":{"01":{"kpu":657,"kawalPemilu":657},"02":{"kpu":235,"kawalPemilu":235}}},"40810":{"id":40810,"name":"JATIREJO","ts":1556211525,"tpsCount":16,"tpsDiffCount":0,"votes":{"01":{"kpu":2210,"kawalPemilu":2210},"02":{"kpu":688,"kawalPemilu":688}}},"40812":{"id":40812,"name":"SIDOKARE","ts":1556211527,"tpsCount":16,"tpsDiffCount":0,"votes":{"01":{"kpu":2218,"kawalPemilu":2218},"02":{"kpu":488,"kawalPemilu":488}}},"40813":{"id":40813,"name":"TEGALSARI BARAT","ts":1556211529,"tpsCount":17,"tpsDiffCount":0,"votes":{"01":{"kpu":1862,"kawalPemilu":1862},"02":{"kpu":461,"kawalPemilu":461}}},"40801":{"id":40801,"name":"KARANGTALOK","ts":1556211510,"tpsCount":1,"tpsDiffCount":0,"votes":{"01":{"kpu":158,"kawalPemilu":158},"02":{"kpu":24,"kawalPemilu":24}}},"40803":{"id":40803,"name":"BLIMBING","ts":1556211515,"tpsCount":4,"tpsDiffCount":1,"votes":{"01":{"kpu":579,"kawalPemilu":580},"02":{"kpu":127,"kawalPemilu":124}}}}}}