{"status":"ok","data":{"regionNames":["IDN","KALIMANTAN TIMUR","KOTA SAMARINDA","SUNGAI KUNJANG","TELUK LERONG ULU"],"regionIds":[0,64111,65567,65599,65604],"ts":1556236391,"tpsDiffCount":0,"tpsCount":28,"votes":{"01":{"kpu":1932,"kawalPemilu":1932},"02":{"kpu":3416,"kawalPemilu":3416}},"childs":{"1":{"name":"001","ts":1556236391,"votes":{"01":{"kpu":54,"kawalPemilu":54},"02":{"kpu":140,"kawalPemilu":140}}},"8":{"name":"008","ts":1556236391,"votes":{"01":{"kpu":90,"kawalPemilu":90},"02":{"kpu":95,"kawalPemilu":95}}},"10":{"name":"010","ts":1556236391,"votes":{"01":{"kpu":80,"kawalPemilu":80},"02":{"kpu":149,"kawalPemilu":149}}},"11":{"name":"011","ts":1556236391,"votes":{"01":{"kpu":107,"kawalPemilu":107},"02":{"kpu":110,"kawalPemilu":110}}},"12":{"name":"012","ts":1556236391,"votes":{"01":{"kpu":47,"kawalPemilu":47},"02":{"kpu":107,"kawalPemilu":107}}},"15":{"name":"015","ts":1556236391,"votes":{"01":{"kpu":52,"kawalPemilu":52},"02":{"kpu":171,"kawalPemilu":171}}},"16":{"name":"016","ts":1556236391,"votes":{"01":{"kpu":79,"kawalPemilu":79},"02":{"kpu":142,"kawalPemilu":142}}},"17":{"name":"017","ts":1556236391,"votes":{"01":{"kpu":80,"kawalPemilu":80},"02":{"kpu":135,"kawalPemilu":135}}},"19":{"name":"019","ts":1556236391,"votes":{"01":{"kpu":60,"kawalPemilu":60},"02":{"kpu":127,"kawalPemilu":127}}},"20":{"name":"020","ts":1556236391,"votes":{"01":{"kpu":116,"kawalPemilu":116},"02":{"kpu":110,"kawalPemilu":110}}},"21":{"name":"021","ts":1556236391,"votes":{"01":{"kpu":44,"kawalPemilu":44},"02":{"kpu":100,"kawalPemilu":100}}},"23":{"name":"023","ts":1556236391,"votes":{"01":{"kpu":97,"kawalPemilu":97},"02":{"kpu":79,"kawalPemilu":79}}},"24":{"name":"024","ts":1556236391,"votes":{"01":{"kpu":59,"kawalPemilu":59},"02":{"kpu":106,"kawalPemilu":106}}},"25":{"name":"025","ts":1556236391,"votes":{"01":{"kpu":63,"kawalPemilu":63},"02":{"kpu":121,"kawalPemilu":121}}},"26":{"name":"026","ts":1556236391,"votes":{"01":{"kpu":65,"kawalPemilu":65},"02":{"kpu":153,"kawalPemilu":153}}},"28":{"name":"028","ts":1556236391,"votes":{"01":{"kpu":49,"kawalPemilu":49},"02":{"kpu":167,"kawalPemilu":167}}},"29":{"name":"029","ts":1556236391,"votes":{"01":{"kpu":51,"kawalPemilu":51},"02":{"kpu":166,"kawalPemilu":166}}},"30":{"name":"030","ts":1556236391,"votes":{"01":{"kpu":97,"kawalPemilu":97},"02":{"kpu":127,"kawalPemilu":127}}},"31":{"name":"031","ts":1556236391,"votes":{"01":{"kpu":45,"kawalPemilu":45},"02":{"kpu":84,"kawalPemilu":84}}},"33":{"name":"033","ts":1556236391,"votes":{"01":{"kpu":82,"kawalPemilu":82},"02":{"kpu":159,"kawalPemilu":159}}},"34":{"name":"034","ts":1556236391,"votes":{"01":{"kpu":28,"kawalPemilu":28},"02":{"kpu":103,"kawalPemilu":103}}},"36":{"name":"036","ts":1556236391,"votes":{"01":{"kpu":76,"kawalPemilu":76},"02":{"kpu":92,"kawalPemilu":92}}},"38":{"name":"038","ts":1556236391,"votes":{"01":{"kpu":99,"kawalPemilu":99},"02":{"kpu":127,"kawalPemilu":127}}},"39":{"name":"039","ts":1556236391,"votes":{"01":{"kpu":86,"kawalPemilu":86},"02":{"kpu":86,"kawalPemilu":86}}},"41":{"name":"041","ts":1556236391,"votes":{"01":{"kpu":80,"kawalPemilu":80},"02":{"kpu":132,"kawalPemilu":132}}},"42":{"name":"042","ts":1556236391,"votes":{"01":{"kpu":21,"kawalPemilu":21},"02":{"kpu":87,"kawalPemilu":87}}},"9":{"name":"009","ts":1556236391,"votes":{"01":{"kpu":93,"kawalPemilu":93},"02":{"kpu":107,"kawalPemilu":107}}},"14":{"name":"014","ts":1556236391,"votes":{"01":{"kpu":32,"kawalPemilu":32},"02":{"kpu":134,"kawalPemilu":134}}}}}}