{"status":"ok","data":{"regionNames":["IDN","MALUKU UTARA","KEPULAUAN SULA"],"regionIds":[0,77085,77858],"ts":1556249523,"tpsDiffCount":0,"tpsCount":12,"votes":{"01":{"kpu":502,"kawalPemilu":502},"02":{"kpu":1749,"kawalPemilu":1749}},"childs":{"77890":{"id":77890,"name":"MANGOLI BARAT","ts":1556249504,"tpsCount":4,"tpsDiffCount":0,"votes":{"01":{"kpu":65,"kawalPemilu":65},"02":{"kpu":610,"kawalPemilu":610}}},"77914":{"id":77914,"name":"MANGOLI TENGAH","ts":1556249517,"tpsCount":4,"tpsDiffCount":0,"votes":{"01":{"kpu":108,"kawalPemilu":108},"02":{"kpu":712,"kawalPemilu":712}}},"77920":{"id":77920,"name":"MANGOLI SELATAN","ts":1556249523,"tpsCount":4,"tpsDiffCount":0,"votes":{"01":{"kpu":329,"kawalPemilu":329},"02":{"kpu":427,"kawalPemilu":427}}}}}}