{"status":"ok","data":{"regionNames":["IDN","JAWA TIMUR","JOMBANG","MOJOAGUNG"],"regionIds":[0,42385,47001,47073],"ts":1556219140,"tpsDiffCount":0,"tpsCount":20,"votes":{"01":{"kpu":2798,"kawalPemilu":2798},"02":{"kpu":853,"kawalPemilu":853}},"childs":{"47084":{"id":47084,"name":"DUKUHDIMORO","ts":1556219135,"tpsCount":1,"tpsDiffCount":0,"votes":{"01":{"kpu":158,"kawalPemilu":158},"02":{"kpu":27,"kawalPemilu":27}}},"47082":{"id":47082,"name":"MOJOTRISNO","ts":1556219132,"tpsCount":1,"tpsDiffCount":0,"votes":{"01":{"kpu":130,"kawalPemilu":130},"02":{"kpu":39,"kawalPemilu":39}}},"47083":{"id":47083,"name":"TANGGALREJO","ts":1556219134,"tpsCount":1,"tpsDiffCount":0,"votes":{"01":{"kpu":163,"kawalPemilu":163},"02":{"kpu":44,"kawalPemilu":44}}},"47085":{"id":47085,"name":"MIAGAN","ts":1556219137,"tpsCount":1,"tpsDiffCount":0,"votes":{"01":{"kpu":150,"kawalPemilu":150},"02":{"kpu":47,"kawalPemilu":47}}},"47086":{"id":47086,"name":"MANCILAN","ts":1556219139,"tpsCount":1,"tpsDiffCount":0,"votes":{"01":{"kpu":140,"kawalPemilu":140},"02":{"kpu":35,"kawalPemilu":35}}},"47087":{"id":47087,"name":"BETEK","ts":1556219140,"tpsCount":15,"tpsDiffCount":0,"votes":{"01":{"kpu":2057,"kawalPemilu":2057},"02":{"kpu":661,"kawalPemilu":661}}}}}}