{"status":"ok","data":{"regionNames":["IDN","SULAWESI TENGGARA","KOLAKA TIMUR","LADONGI","WUNGGULOKO"],"regionIds":[0,72551,928076,72622,72632],"ts":1556245921,"tpsDiffCount":0,"tpsCount":3,"votes":{"01":{"kpu":294,"kawalPemilu":294},"02":{"kpu":122,"kawalPemilu":122}},"childs":{"1":{"name":"001","ts":1556245921,"votes":{"01":{"kpu":105,"kawalPemilu":105},"02":{"kpu":41,"kawalPemilu":41}}},"2":{"name":"002","ts":1556245921,"votes":{"01":{"kpu":105,"kawalPemilu":105},"02":{"kpu":50,"kawalPemilu":50}}},"3":{"name":"003","ts":1556245921,"votes":{"01":{"kpu":84,"kawalPemilu":84},"02":{"kpu":31,"kawalPemilu":31}}}}}}