{"status":"ok","data":{"regionNames":["IDN","JAWA TENGAH","BANJARNEGARA"],"regionIds":[0,32676,33603],"ts":1556203440,"tpsDiffCount":7,"tpsCount":1212,"votes":{"01":{"kpu":150526,"kawalPemilu":150487},"02":{"kpu":68315,"kawalPemilu":68206}},"childs":{"33604":{"id":33604,"name":"SUSUKAN","ts":1556203153,"tpsCount":60,"tpsDiffCount":1,"votes":{"01":{"kpu":8020,"kawalPemilu":8002},"02":{"kpu":2151,"kawalPemilu":2138}}},"33620":{"id":33620,"name":"PURWOREJO KLAMPOK","ts":1556203164,"tpsCount":32,"tpsDiffCount":0,"votes":{"01":{"kpu":4754,"kawalPemilu":4754},"02":{"kpu":1560,"kawalPemilu":1560}}},"33629":{"id":33629,"name":"MANDIRAJA","ts":1556203184,"tpsCount":122,"tpsDiffCount":0,"votes":{"01":{"kpu":18317,"kawalPemilu":18317},"02":{"kpu":4266,"kawalPemilu":4266}}},"33646":{"id":33646,"name":"PURWONEGORO","ts":1556203195,"tpsCount":54,"tpsDiffCount":0,"votes":{"01":{"kpu":7713,"kawalPemilu":7713},"02":{"kpu":2737,"kawalPemilu":2737}}},"33660":{"id":33660,"name":"BAWANG","ts":1556203216,"tpsCount":118,"tpsDiffCount":1,"votes":{"01":{"kpu":14205,"kawalPemilu":14188},"02":{"kpu":7202,"kawalPemilu":7236}}},"33679":{"id":33679,"name":"BANJARNEGARA","ts":1556203237,"tpsCount":146,"tpsDiffCount":1,"votes":{"01":{"kpu":16055,"kawalPemilu":16055},"02":{"kpu":12006,"kawalPemilu":11976}}},"33693":{"id":33693,"name":"SIGALUH","ts":1556203242,"tpsCount":9,"tpsDiffCount":0,"votes":{"01":{"kpu":908,"kawalPemilu":908},"02":{"kpu":732,"kawalPemilu":732}}},"33709":{"id":33709,"name":"MADUKARA","ts":1556203252,"tpsCount":14,"tpsDiffCount":0,"votes":{"01":{"kpu":1854,"kawalPemilu":1854},"02":{"kpu":896,"kawalPemilu":896}}},"33730":{"id":33730,"name":"BANJARMANGU","ts":1556203274,"tpsCount":73,"tpsDiffCount":0,"votes":{"01":{"kpu":8643,"kawalPemilu":8643},"02":{"kpu":4728,"kawalPemilu":4728}}},"33748":{"id":33748,"name":"WANADADI","ts":1556203289,"tpsCount":54,"tpsDiffCount":1,"votes":{"01":{"kpu":5526,"kawalPemilu":5526},"02":{"kpu":4616,"kawalPemilu":4516}}},"33760":{"id":33760,"name":"RAKIT","ts":1556203299,"tpsCount":59,"tpsDiffCount":0,"votes":{"01":{"kpu":7988,"kawalPemilu":7988},"02":{"kpu":3542,"kawalPemilu":3542}}},"33772":{"id":33772,"name":"PUNGGELAN","ts":1556203327,"tpsCount":74,"tpsDiffCount":0,"votes":{"01":{"kpu":8784,"kawalPemilu":8784},"02":{"kpu":3194,"kawalPemilu":3194}}},"33790":{"id":33790,"name":"KARANGKOBAR","ts":1556203339,"tpsCount":37,"tpsDiffCount":0,"votes":{"01":{"kpu":4333,"kawalPemilu":4333},"02":{"kpu":1473,"kawalPemilu":1473}}},"33804":{"id":33804,"name":"PAGENTAN","ts":1556203355,"tpsCount":52,"tpsDiffCount":1,"votes":{"01":{"kpu":5755,"kawalPemilu":5755},"02":{"kpu":2957,"kawalPemilu":2947}}},"33821":{"id":33821,"name":"PEJAWARAN","ts":1556203373,"tpsCount":56,"tpsDiffCount":0,"votes":{"01":{"kpu":6687,"kawalPemilu":6687},"02":{"kpu":3451,"kawalPemilu":3451}}},"33839":{"id":33839,"name":"BATUR","ts":1556203383,"tpsCount":42,"tpsDiffCount":1,"votes":{"01":{"kpu":4206,"kawalPemilu":4216},"02":{"kpu":4358,"kawalPemilu":4368}}},"33848":{"id":33848,"name":"WANAYASA","ts":1556203397,"tpsCount":54,"tpsDiffCount":0,"votes":{"01":{"kpu":7036,"kawalPemilu":7036},"02":{"kpu":2984,"kawalPemilu":2984}}},"33866":{"id":33866,"name":"KALIBENING","ts":1556203409,"tpsCount":49,"tpsDiffCount":0,"votes":{"01":{"kpu":5261,"kawalPemilu":5261},"02":{"kpu":1683,"kawalPemilu":1683}}},"33883":{"id":33883,"name":"PANDANARUM","ts":1556203418,"tpsCount":35,"tpsDiffCount":0,"votes":{"01":{"kpu":4979,"kawalPemilu":4979},"02":{"kpu":993,"kawalPemilu":993}}},"33892":{"id":33892,"name":"PAGEDONGAN","ts":1556203440,"tpsCount":72,"tpsDiffCount":1,"votes":{"01":{"kpu":9502,"kawalPemilu":9488},"02":{"kpu":2786,"kawalPemilu":2786}}}}}}