{"status":"ok","data":[{"id":74925,"name":"HUTADAA","provinceId":74716,"provinceName":"GORONTALO","regencyId":74717,"regencyName":"GORONTALO","districtId":74924,"districtName":"TALAGA JAYA"},{"id":74926,"name":"BUHU","provinceId":74716,"provinceName":"GORONTALO","regencyId":74717,"regencyName":"GORONTALO","districtId":74924,"districtName":"TALAGA JAYA"},{"id":74927,"name":"LUWOO","provinceId":74716,"provinceName":"GORONTALO","regencyId":74717,"regencyName":"GORONTALO","districtId":74924,"districtName":"TALAGA JAYA"},{"id":74928,"name":"BUNGGALO","provinceId":74716,"provinceName":"GORONTALO","regencyId":74717,"regencyName":"GORONTALO","districtId":74924,"districtName":"TALAGA JAYA"},{"id":74929,"name":"BULOTA","provinceId":74716,"provinceName":"GORONTALO","regencyId":74717,"regencyName":"GORONTALO","districtId":74924,"districtName":"TALAGA JAYA"}]}