{"status":"ok","data":{"regionNames":["IDN","NUSA TENGGARA TIMUR","SUMBA BARAT DAYA","KODI","ONGGOL"],"regionIds":[0,55065,57935,58015,58025],"ts":1556229560,"tpsDiffCount":0,"tpsCount":6,"votes":{"01":{"kpu":608,"kawalPemilu":608},"02":{"kpu":38,"kawalPemilu":38}},"childs":{"1":{"name":"001","ts":1556229560,"votes":{"01":{"kpu":122,"kawalPemilu":122},"02":{"kpu":17,"kawalPemilu":17}}},"2":{"name":"002","ts":1556229560,"votes":{"01":{"kpu":128,"kawalPemilu":128},"02":{"kpu":4,"kawalPemilu":4}}},"4":{"name":"004","ts":1556229560,"votes":{"01":{"kpu":100,"kawalPemilu":100},"02":{"kpu":7,"kawalPemilu":7}}},"5":{"name":"005","ts":1556229560,"votes":{"01":{"kpu":129,"kawalPemilu":129},"02":{"kpu":5,"kawalPemilu":5}}},"6":{"name":"006","ts":1556229560,"votes":{"01":{"kpu":71,"kawalPemilu":71},"02":{"kpu":3,"kawalPemilu":3}}},"7":{"name":"007","ts":1556229560,"votes":{"01":{"kpu":58,"kawalPemilu":58},"02":{"kpu":2,"kawalPemilu":2}}}}}}