{"status":"ok","data":[{"id":64062,"name":"ALALAK TENGAH","provinceId":61965,"provinceName":"KALIMANTAN SELATAN","regencyId":64027,"regencyName":"KOTA BANJARMASIN","districtId":64061,"districtName":"BANJARMASIN UTARA"},{"id":64063,"name":"ALALAK UTARA","provinceId":61965,"provinceName":"KALIMANTAN SELATAN","regencyId":64027,"regencyName":"KOTA BANJARMASIN","districtId":64061,"districtName":"BANJARMASIN UTARA"},{"id":64064,"name":"ALALAK SELATAN","provinceId":61965,"provinceName":"KALIMANTAN SELATAN","regencyId":64027,"regencyName":"KOTA BANJARMASIN","districtId":64061,"districtName":"BANJARMASIN UTARA"},{"id":64065,"name":"SUNGAI JINGAH","provinceId":61965,"provinceName":"KALIMANTAN SELATAN","regencyId":64027,"regencyName":"KOTA BANJARMASIN","districtId":64061,"districtName":"BANJARMASIN UTARA"},{"id":64066,"name":"SUNGAI MIAI","provinceId":61965,"provinceName":"KALIMANTAN SELATAN","regencyId":64027,"regencyName":"KOTA BANJARMASIN","districtId":64061,"districtName":"BANJARMASIN UTARA"},{"id":64067,"name":"SURGI MUFTI","provinceId":61965,"provinceName":"KALIMANTAN SELATAN","regencyId":64027,"regencyName":"KOTA BANJARMASIN","districtId":64061,"districtName":"BANJARMASIN UTARA"},{"id":64068,"name":"PANGERAN","provinceId":61965,"provinceName":"KALIMANTAN SELATAN","regencyId":64027,"regencyName":"KOTA BANJARMASIN","districtId":64061,"districtName":"BANJARMASIN UTARA"},{"id":64069,"name":"ANTASAN KECIL TIMUR","provinceId":61965,"provinceName":"KALIMANTAN SELATAN","regencyId":64027,"regencyName":"KOTA BANJARMASIN","districtId":64061,"districtName":"BANJARMASIN UTARA"},{"id":64070,"name":"KUIN UTARA","provinceId":61965,"provinceName":"KALIMANTAN SELATAN","regencyId":64027,"regencyName":"KOTA BANJARMASIN","districtId":64061,"districtName":"BANJARMASIN UTARA"},{"id":64071,"name":"SUNGAI ANDAI","provinceId":61965,"provinceName":"KALIMANTAN SELATAN","regencyId":64027,"regencyName":"KOTA BANJARMASIN","districtId":64061,"districtName":"BANJARMASIN UTARA"}]}