{"status":"ok","data":{"regionNames":["IDN","JAWA BARAT","BOGOR","MEGAMENDUNG"],"regionIds":[0,26141,26142,26460],"ts":1556194389,"tpsDiffCount":2,"tpsCount":15,"votes":{"01":{"kpu":639,"kawalPemilu":639},"02":{"kpu":2268,"kawalPemilu":2167}},"childs":{"26461":{"id":26461,"name":"SUKAMAJU","ts":1556194372,"tpsCount":2,"tpsDiffCount":1,"votes":{"01":{"kpu":37,"kawalPemilu":37},"02":{"kpu":337,"kawalPemilu":237}}},"26469":{"id":26469,"name":"CIPAYUNG GIRANG","ts":1556194386,"tpsCount":2,"tpsDiffCount":0,"votes":{"01":{"kpu":86,"kawalPemilu":86},"02":{"kpu":264,"kawalPemilu":264}}},"26470":{"id":26470,"name":"SUKAMAHI","ts":1556194387,"tpsCount":2,"tpsDiffCount":0,"votes":{"01":{"kpu":131,"kawalPemilu":131},"02":{"kpu":360,"kawalPemilu":360}}},"88176":{"id":88176,"name":"PASIR ANGIN","ts":1556194389,"tpsCount":3,"tpsDiffCount":0,"votes":{"01":{"kpu":98,"kawalPemilu":98},"02":{"kpu":431,"kawalPemilu":431}}},"26462":{"id":26462,"name":"KUTA","ts":1556194374,"tpsCount":1,"tpsDiffCount":1,"votes":{"01":{"kpu":11,"kawalPemilu":11},"02":{"kpu":152,"kawalPemilu":151}}},"26463":{"id":26463,"name":"GADOG","ts":1556194375,"tpsCount":1,"tpsDiffCount":0,"votes":{"01":{"kpu":47,"kawalPemilu":47},"02":{"kpu":176,"kawalPemilu":176}}},"26464":{"id":26464,"name":"SUKAKARYA","ts":1556194377,"tpsCount":2,"tpsDiffCount":0,"votes":{"01":{"kpu":93,"kawalPemilu":93},"02":{"kpu":292,"kawalPemilu":292}}},"26466":{"id":26466,"name":"CIPAYUNG","ts":1556194381,"tpsCount":2,"tpsDiffCount":0,"votes":{"01":{"kpu":136,"kawalPemilu":136},"02":{"kpu":256,"kawalPemilu":256}}}}}}