{"status":"ok","data":[{"id":15522,"name":"LUBUK DALAM","provinceId":14086,"provinceName":"RIAU","regencyId":15412,"regencyName":"SIAK","districtId":15521,"districtName":"LUBUK DALAM"},{"id":15523,"name":"RAWANG KAO","provinceId":14086,"provinceName":"RIAU","regencyId":15412,"regencyName":"SIAK","districtId":15521,"districtName":"LUBUK DALAM"},{"id":15524,"name":"SRI GADING","provinceId":14086,"provinceName":"RIAU","regencyId":15412,"regencyName":"SIAK","districtId":15521,"districtName":"LUBUK DALAM"},{"id":15525,"name":"SIALANG BARU","provinceId":14086,"provinceName":"RIAU","regencyId":15412,"regencyName":"SIAK","districtId":15521,"districtName":"LUBUK DALAM"},{"id":15526,"name":"SIALANG PALAS","provinceId":14086,"provinceName":"RIAU","regencyId":15412,"regencyName":"SIAK","districtId":15521,"districtName":"LUBUK DALAM"},{"id":15527,"name":"EMPANG BARU","provinceId":14086,"provinceName":"RIAU","regencyId":15412,"regencyName":"SIAK","districtId":15521,"districtName":"LUBUK DALAM"},{"id":88283,"name":"RAWANG KAO BARAT","provinceId":14086,"provinceName":"RIAU","regencyId":15412,"regencyName":"SIAK","districtId":15521,"districtName":"LUBUK DALAM"}]}